airflow_livy/__init__.py
airflow_livy/batch.py
airflow_livy/session.py
airflow_livy_operators-0.6.dist-info/LICENSE
airflow_livy_operators-0.6.dist-info/METADATA
airflow_livy_operators-0.6.dist-info/WHEEL
airflow_livy_operators-0.6.dist-info/top_level.txt
airflow_livy_operators-0.6.dist-info/RECORD
