Metadata-Version: 2.1
Name: airflow-livy-operators
Version: 0.6
Summary: Lets Airflow DAGs run Spark jobs via Livy: sessions and/or batches.
Home-page: https://github.com/panovvv/airflow-livy-operators
Author: Vadim Panov
Author-email: headcra6@gmail.com
License: MIT License
Platform: UNKNOWN
Classifier: Programming Language :: Python :: 3.7
Classifier: Programming Language :: Python :: 3.8
Classifier: Programming Language :: Python :: 3.9
Requires-Python: >=3.7
License-File: LICENSE
